odoo/addons/edi_voxel_account_invoice_oca/README.rst
odoo/addons/edi_voxel_account_invoice_oca/__init__.py
odoo/addons/edi_voxel_account_invoice_oca/__manifest__.py
odoo/addons/edi_voxel_account_invoice_oca/data/ir_cron_data.xml
odoo/addons/edi_voxel_account_invoice_oca/data/queue_job_function_data.xml
odoo/addons/edi_voxel_account_invoice_oca/i18n/edi_voxel_account_invoice_oca.pot
odoo/addons/edi_voxel_account_invoice_oca/i18n/es.po
odoo/addons/edi_voxel_account_invoice_oca/i18n/it.po
odoo/addons/edi_voxel_account_invoice_oca/models/__init__.py
odoo/addons/edi_voxel_account_invoice_oca/models/account_move.py
odoo/addons/edi_voxel_account_invoice_oca/models/res_company.py
odoo/addons/edi_voxel_account_invoice_oca/models/res_config_settings.py
odoo/addons/edi_voxel_account_invoice_oca/readme/CONFIGURE.md
odoo/addons/edi_voxel_account_invoice_oca/readme/CONTRIBUTORS.md
odoo/addons/edi_voxel_account_invoice_oca/readme/DESCRIPTION.md
odoo/addons/edi_voxel_account_invoice_oca/readme/USAGE.md
odoo/addons/edi_voxel_account_invoice_oca/reports/__init__.py
odoo/addons/edi_voxel_account_invoice_oca/reports/report_voxel_invoice.py
odoo/addons/edi_voxel_account_invoice_oca/static/description/icon.png
odoo/addons/edi_voxel_account_invoice_oca/static/description/index.html
odoo/addons/edi_voxel_account_invoice_oca/tests/__init__.py
odoo/addons/edi_voxel_account_invoice_oca/tests/test_voxel_account_invoice.py
odoo/addons/edi_voxel_account_invoice_oca/views/account_move_views.xml
odoo/addons/edi_voxel_account_invoice_oca/views/report_voxel_invoice.xml
odoo/addons/edi_voxel_account_invoice_oca/views/res_company_view.xml
odoo/addons/edi_voxel_account_invoice_oca/views/res_config_settings_views.xml
odoo_addon_edi_voxel_account_invoice_oca-18.0.1.0.1.dist-info/METADATA
odoo_addon_edi_voxel_account_invoice_oca-18.0.1.0.1.dist-info/WHEEL
odoo_addon_edi_voxel_account_invoice_oca-18.0.1.0.1.dist-info/top_level.txt
odoo_addon_edi_voxel_account_invoice_oca-18.0.1.0.1.dist-info/RECORD
