Metadata-Version: 2.1
Name: odoo-addon-edi_voxel_account_invoice_oca
Version: 18.0.1.0.1
Requires-Python: >=3.10
Requires-Dist: odoo-addon-edi_voxel_oca==18.0.*
Requires-Dist: odoo-addon-stock_picking_invoice_link==18.0.*
Requires-Dist: odoo==18.0.*
Summary: Sends account invoices to Voxel.
Home-page: https://github.com/OCA/edi-voxel
License: AGPL-3
Author: Tecnativa, Odoo Community Association (OCA)
Author-email: support@odoo-community.org
Classifier: Programming Language :: Python
Classifier: Framework :: Odoo
Classifier: Framework :: Odoo :: 18.0
Classifier: License :: OSI Approved :: GNU Affero General Public License v3
Classifier: Development Status :: 5 - Production/Stable
